plugflow/__init__.py
plugflow/_version.py
plugflow/base.py
plugflow/loader.py
plugflow/manager.py
plugflow/watcher.py
plugflow-1.0.3.dist-info/licenses/LICENSE
plugflow-1.0.3.dist-info/METADATA
plugflow-1.0.3.dist-info/WHEEL
plugflow-1.0.3.dist-info/top_level.txt
plugflow-1.0.3.dist-info/RECORD
