Metadata-Version: 2.4
Name: plugflow
Version: 1.0.3
Summary: A powerful Python plugin system with dynamic loading and hot-reload capabilities.
Home-page: https://github.com/keklick1337/plugflow
Author: Vladislav Tislenko
Author-email: python@trustcrypt.com
License: MIT
Project-URL: Documentation, https://github.com/keklick1337/plugflow
Project-URL: Bug Reports, https://github.com/keklick1337/plugflow/issues
Project-URL: Source Code, https://github.com/keklick1337/plugflow
Project-URL: Homepage, https://github.com/keklick1337/plugflow
Keywords: plugin,plugins,dynamic-loading,hot-reload,extensible,plugin-system,python-plugins
Classifier: Development Status :: 4 - Beta
Classifier: Intended Audience :: Developers
Classifier: Topic :: Software Development :: Libraries :: Python Modules
Classifier: Topic :: System :: Systems Administration
Classifier: Topic :: Utilities
Classifier: Programming Language :: Python :: 3
Classifier: Programming Language :: Python :: 3.8
Classifier: Programming Language :: Python :: 3.9
Classifier: Programming Language :: Python :: 3.10
Classifier: Programming Language :: Python :: 3.11
Classifier: Programming Language :: Python :: 3.12
Classifier: Programming Language :: Python :: 3.13
Classifier: Programming Language :: Python :: 3 :: Only
Classifier: Operating System :: OS Independent
Requires-Python: >=3.8
License-File: LICENSE
Provides-Extra: dev
Requires-Dist: pytest; extra == "dev"
Requires-Dist: pytest-cov; extra == "dev"
Requires-Dist: black; extra == "dev"
Requires-Dist: isort; extra == "dev"
Dynamic: author
Dynamic: author-email
Dynamic: classifier
Dynamic: description
Dynamic: description-content-type
Dynamic: home-page
Dynamic: keywords
Dynamic: license
Dynamic: license-file
Dynamic: project-url
Dynamic: provides-extra
Dynamic: requires-python
Dynamic: summary
